conduit/__init__.py
conduit/__version__.py
conduit/client.py
conduit/descriptors.py
conduit/exceptions.py
conduit/py.typed
conduit/server.py
conduit/backpressure/__init__.py
conduit/backpressure/flow_control.py
conduit/connection/__init__.py
conduit/connection/connection.py
conduit/connection/pool.py
conduit/data/__init__.py
conduit/data/connection.py
conduit/data/descriptors.py
conduit/data/messages.py
conduit/data/rpc.py
conduit/heartbeat/__init__.py
conduit/heartbeat/monitor.py
conduit/messages/__init__.py
conduit/messages/message.py
conduit/messages/queue.py
conduit/messages/router.py
conduit/metrics/__init__.py
conduit/metrics/metrics.py
conduit/pool/__init__.py
conduit/pool/client_pool.py
conduit/protocol/__init__.py
conduit/protocol/decoder.py
conduit/protocol/encoder.py
conduit/protocol/format.py
conduit/ratelimit/__init__.py
conduit/ratelimit/limiter.py
conduit/response/__init__.py
conduit/response/error.py
conduit/response/response.py
conduit/rpc/__init__.py
conduit/rpc/dispatcher.py
conduit/rpc/helpers.py
conduit/rpc/registry.py
conduit/rpc/rpc_class.py
conduit/streaming/__init__.py
conduit/streaming/stream.py
conduit/transfer/__init__.py
conduit/transfer/file_transfer.py
conduit/transport/__init__.py
conduit/transport/auth.py
conduit/transport/connection_state.py
conduit/transport/tcp_socket.py
conduit/transport/tls.py
netconduit-5.0.0.dist-info/licenses/LICENSE
netconduit-5.0.0.dist-info/METADATA
netconduit-5.0.0.dist-info/WHEEL
netconduit-5.0.0.dist-info/top_level.txt
netconduit-5.0.0.dist-info/RECORD
