Metadata-Version: 2.4
Name: netconduit
Version: 5.0.0
Summary: Production-ready async bidirectional TCP communication library with custom binary protocol, type-safe RPC, and Pydantic integration
Author-email: Kaede Dev - Kento Hinode <cleaverdeath@gmail.com>
Maintainer-email: Kaede Dev - Kento Hinode <cleaverdeath@gmail.com>
License: MIT
Project-URL: Homepage, https://github.com/DarsheeeGamer/NetConduit
Project-URL: Documentation, https://github.com/DarsheeeGamer/NetConduit#readme
Project-URL: Repository, https://github.com/DarsheeeGamer/NetConduit
Project-URL: Issues, https://github.com/DarsheeeGamer/NetConduit/issues
Project-URL: Changelog, https://github.com/DarsheeeGamer/NetConduit/blob/main/CHANGELOG.md
Keywords: networking,tcp,async,asyncio,rpc,bidirectional,communication,protocol,binary-protocol,pydantic,msgpack,server,client,socket,real-time
Classifier: Development Status :: 4 - Beta
Classifier: Intended Audience :: Developers
Classifier: License :: OSI Approved :: MIT License
Classifier: Operating System :: OS Independent
Classifier: Programming Language :: Python :: 3
Classifier: Programming Language :: Python :: 3.10
Classifier: Programming Language :: Python :: 3.11
Classifier: Programming Language :: Python :: 3.12
Classifier: Programming Language :: Python :: 3.13
Classifier: Topic :: Communications
Classifier: Topic :: Internet
Classifier: Topic :: System :: Networking
Classifier: Topic :: Software Development :: Libraries :: Python Modules
Classifier: Framework :: AsyncIO
Classifier: Typing :: Typed
Requires-Python: >=3.10
License-File: LICENSE
Requires-Dist: pydantic>=2.0
Requires-Dist: msgpack>=1.0
Provides-Extra: dev
Requires-Dist: pytest>=7.0; extra == "dev"
Requires-Dist: pytest-asyncio>=0.21; extra == "dev"
Requires-Dist: pytest-cov>=4.0; extra == "dev"
Requires-Dist: mypy>=1.0; extra == "dev"
Requires-Dist: black>=23.0; extra == "dev"
Requires-Dist: ruff>=0.1; extra == "dev"
Provides-Extra: docs
Requires-Dist: sphinx>=7.0; extra == "docs"
Requires-Dist: sphinx-rtd-theme>=2.0; extra == "docs"
Requires-Dist: myst-parser>=2.0; extra == "docs"
Dynamic: license-file
